rocco/__init__.py
rocco/constants.py
rocco/dm6.sizes
rocco/dm_params.csv
rocco/hg19.sizes
rocco/hg38.sizes
rocco/hg_params.csv
rocco/mm10.sizes
rocco/mm39.sizes
rocco/mm_params.csv
rocco/readtracks.py
rocco/rocco.py
rocco/scores.py
rocco-1.6.3.dist-info/METADATA
rocco-1.6.3.dist-info/WHEEL
rocco-1.6.3.dist-info/entry_points.txt
rocco-1.6.3.dist-info/top_level.txt
rocco-1.6.3.dist-info/RECORD
