Metadata-Version: 2.2
Name: rocco
Version: 1.6.3
Summary: Multisample Consensus Peak Calling via Convex Optimization
Home-page: https://github.com/nolan-h-hamilton/rocco
Author: Nolan Holt Hamilton
Author-email: nolan.hamilton@unc.edu
License: MIT
Keywords: genomics,functional genomics,epigenomics,epigenetics,peak calling,chromatin accessibility,chromatin,consensus peak,DNase,ATAC,ChIP-seq
Classifier: Development Status :: 4 - Beta
Classifier: Intended Audience :: Science/Research
Classifier: License :: OSI Approved :: MIT License
Classifier: Programming Language :: Python :: 3
Classifier: Topic :: Scientific/Engineering :: Bio-Informatics
Requires-Python: >=3.9, <4
Requires-Dist: ortools>=9.10
Requires-Dist: numpy
Requires-Dist: scipy
Requires-Dist: pandas
Requires-Dist: pybedtools
Requires-Dist: pyBigWig
Requires-Dist: deeptools
Requires-Dist: pysam
Requires-Dist: myst-parser
Provides-Extra: pytest
Requires-Dist: pytest>=6.0.1; extra == "pytest"
Dynamic: author
Dynamic: author-email
Dynamic: classifier
Dynamic: description
Dynamic: description-content-type
Dynamic: home-page
Dynamic: keywords
Dynamic: license
Dynamic: provides-extra
Dynamic: requires-dist
Dynamic: requires-python
Dynamic: summary
